{
  "updated_at": "2026-05-17T00:50:46.639608+00:00",
  "entries": {
    "craigslist_van:7933503143": {
      "url": "https://vancouver.craigslist.org/van/apa/d/vancouver-house-for-rent/7933503143.html",
      "title": "House for Rent",
      "source": "craigslist_van",
      "price_cad": 4000,
      "bedrooms": 4.0,
      "neighborhood": "Boundary/Collingwood",
      "address_text": "Approx map: 49.239700, -123.040700",
      "transit_minutes_to_ubc": 65
    },
    "craigslist_van:7926911474": {
      "url": "https://vancouver.craigslist.org/van/apa/d/richmond-10-minutes-to-ubc-basement/7926911474.html",
      "title": "8-10 Minutes to UBC 1 basement bedroom for rent",
      "source": "craigslist_van",
      "price_cad": 1000,
      "bedrooms": 4.0,
      "neighborhood": "Alma st and W 10th AVE",
      "address_text": "10th AVE, VANCOUVER, BC V6X0C3",
      "transit_minutes_to_ubc": 31
    },
    "craigslist_van:7932565625": {
      "url": "https://vancouver.craigslist.org/van/apa/d/vancouver-plhref2442charming-whole/7932565625.html",
      "title": "(PLH_REF#2442)***Charming Whole 4-Bedroom House with Backyard & Garage",
      "source": "craigslist_van",
      "price_cad": 4800,
      "bedrooms": 4.0,
      "neighborhood": "city of vancouver",
      "address_text": "2442 East 19th Avenue, Vancouver, BC V5M2R9",
      "transit_minutes_to_ubc": 67
    },
    "craigslist_van:7929875795": {
      "url": "https://vancouver.craigslist.org/van/apa/d/vancouver-plhref7969spacious-bedroom/7929875795.html",
      "title": "(PLH_REF#7969)***Spacious 4-Bedroom Family Home in Desirable Marpole \u2014",
      "source": "craigslist_van",
      "price_cad": 4800,
      "bedrooms": 4.0,
      "neighborhood": "Marpole",
      "address_text": "7989 Cambie Street, Vancouver, BC V6P3J4",
      "transit_minutes_to_ubc": 50
    },
    "craigslist_van:7934784292": {
      "url": "https://vancouver.craigslist.org/van/apa/d/vancouver-furnished-room-for-rent-in/7934784292.html",
      "title": "A Furnished Room for Rent in Vancouver",
      "source": "craigslist_van",
      "price_cad": 900,
      "bedrooms": 6.0,
      "neighborhood": "Vancouver",
      "address_text": "1842 W 63rd Ave, Vancouver, BC V6P2J1",
      "transit_minutes_to_ubc": 44
    },
    "craigslist_van:7934782565": {
      "url": "https://vancouver.craigslist.org/van/apa/d/vancouver-furnished-room-for-rent-in/7934782565.html",
      "title": "A Furnished Room for Rent in Vancouver",
      "source": "craigslist_van",
      "price_cad": 1000,
      "bedrooms": 6.0,
      "neighborhood": "Vancouver",
      "address_text": "3550 W. 39th Ave, Vancouver, BC V6N3A5",
      "transit_minutes_to_ubc": 20
    },
    "craigslist_van:7929666902": {
      "url": "https://vancouver.craigslist.org/van/apa/d/vancouver-furnished-room-for-rent-in/7929666902.html",
      "title": "A furnished room for rent in Vancouver",
      "source": "craigslist_van",
      "price_cad": 1000,
      "bedrooms": 6.0,
      "neighborhood": "Vancouver",
      "address_text": "3853 W 15th Ave, Vancouver, BC V6R3A1",
      "transit_minutes_to_ubc": 23
    },
    "craigslist_van:7933972358": {
      "url": "https://vancouver.craigslist.org/van/apa/d/vancouver-new-built-bed-35-bath-laneway/7933972358.html",
      "title": "New Built 4 Bed 3.5 Bath Laneway at E45th",
      "source": "craigslist_van",
      "price_cad": 3100,
      "bedrooms": 4.0,
      "neighborhood": "Vancouver",
      "address_text": "Approx map: 49.223200, -123.043400",
      "transit_minutes_to_ubc": 63
    },
    "craigslist_van:7928626280": {
      "url": "https://vancouver.craigslist.org/van/apa/d/cranbrook-dunbar-house-upstairs-4bd-2ba/7928626280.html",
      "title": "Dunbar House Upstairs 4bd 2ba For Rent",
      "source": "craigslist_van",
      "price_cad": 4800,
      "bedrooms": 4.0,
      "neighborhood": "city of vancouver",
      "address_text": "Dunbar St, Vancouver, BC V6S1W5",
      "transit_minutes_to_ubc": 26
    },
    "craigslist_van:7931966065": {
      "url": "https://vancouver.craigslist.org/van/apa/d/vancouver-bedroom-bathroom-ground-floor/7931966065.html",
      "title": "*** 4 BEDROOM 2 BATHROOM GROUND FLOOR SUITE NANAIMO AND 1ST AVENUE ***",
      "source": "craigslist_van",
      "price_cad": 3400,
      "bedrooms": 4.0,
      "neighborhood": "Vancouver",
      "address_text": "East 1st Avenue, vancouver, BC V5M1A3",
      "transit_minutes_to_ubc": 68
    },
    "craigslist_van:7931923778": {
      "url": "https://vancouver.craigslist.org/van/apa/d/vancouver-master-suite-in-mansion-live/7931923778.html",
      "title": "Master Suite in Mansion - Live with Like-Minded People!",
      "source": "craigslist_van",
      "price_cad": 2700,
      "bedrooms": 8.0,
      "neighborhood": "Shaughnessy",
      "address_text": "Approx map: 49.257500, -123.138800",
      "transit_minutes_to_ubc": 32
    },
    "craigslist_van:7933652997": {
      "url": "https://vancouver.craigslist.org/van/apa/d/surrey-offer-kitchener-rare-spacious/7933652997.html",
      "title": "\ud83c\udfe2 Offer: KITCHENER //RARE spacious and modern 4 BR+3.5 Bath Townhouse",
      "source": "craigslist_van",
      "price_cad": 3750,
      "bedrooms": 4.0,
      "neighborhood": "South Surrey",
      "address_text": "Approx map: 49.050653, -122.782720",
      "transit_minutes_to_ubc": 120
    },
    "craigslist_van:7934253594": {
      "url": "https://vancouver.craigslist.org/van/apa/d/surrey-offer-soho-rare-furnished-br-35/7934253594.html",
      "title": "\ud83c\udfe2 Offer: SOHO // RARE furnished 4 BR + 3.5 Bath Townhouse (1932 sqf)",
      "source": "craigslist_van",
      "price_cad": 3800,
      "bedrooms": 4.0,
      "neighborhood": "South Surrey",
      "address_text": "Approx map: 49.043016, -122.769599",
      "transit_minutes_to_ubc": 122
    },
    "craigslist_van:7931563746": {
      "url": "https://vancouver.craigslist.org/van/apa/d/vancouver-newly-crafted-vancouver-west/7931563746.html",
      "title": "Newly Crafted Vancouver West 1500SF 4bed 3bath Laneway available NOW!",
      "source": "craigslist_van",
      "price_cad": 6000,
      "bedrooms": 4.0,
      "neighborhood": "Point Grey",
      "address_text": "41st Ave, Vancouver, BC V6N1Z1",
      "transit_minutes_to_ubc": 21
    },
    "craigslist_van:7934720914": {
      "url": "https://vancouver.craigslist.org/van/apa/d/vancouver-bedroom-east-vancouver/7934720914.html",
      "title": "4 Bedroom East Vancouver",
      "source": "craigslist_van",
      "price_cad": 2999,
      "bedrooms": 4.0,
      "neighborhood": "East Vancouver",
      "address_text": "6th Avenue, Vancouver, BC V5N5C7",
      "transit_minutes_to_ubc": 55
    },
    "craigslist_van:7934709701": {
      "url": "https://vancouver.craigslist.org/van/apa/d/vancouver-avail-june-1st-lrg-lwr-level/7934709701.html",
      "title": "Avail June 1st lrg lwr. level furn.. suite clse to UBC/Dunbar",
      "source": "craigslist_van",
      "price_cad": 3950,
      "bedrooms": 5.0,
      "neighborhood": "Dunbar near Crown/41st",
      "address_text": "Approx map: 49.230200, -123.189000",
      "transit_minutes_to_ubc": 27
    },
    "craigslist_van:7934172815": {
      "url": "https://vancouver.craigslist.org/van/apa/d/vancouver-brand-new-house-for-rent/7934172815.html",
      "title": "Brand new house for rent Beside the PNE LONG OR SHORT TERM RENTAL",
      "source": "craigslist_van",
      "price_cad": 6000,
      "bedrooms": 4.0,
      "neighborhood": "hastings sunrise",
      "address_text": "Approx map: 49.280700, -123.039700",
      "transit_minutes_to_ubc": 75
    },
    "craigslist_van:7934660646": {
      "url": "https://vancouver.craigslist.org/van/apa/d/coquitlam-spacious-bedroom-den-home/7934660646.html",
      "title": "Spacious 4 Bedroom + Den Home \u2013 Coquitlam",
      "source": "craigslist_van",
      "price_cad": 4500,
      "bedrooms": 4.0,
      "neighborhood": "Coquitlam",
      "address_text": "101 - 914 Rochester Ave, V3K 2W6, BC V3K2W6",
      "transit_minutes_to_ubc": 88
    },
    "craigslist_van:7932674659": {
      "url": "https://vancouver.craigslist.org/van/apa/d/burnaby-entire-bedroom-house-for-rent/7932674659.html",
      "title": "\ud83c\udfe1 Entire 7 Bedroom House for Rent",
      "source": "craigslist_van",
      "price_cad": 5500,
      "bedrooms": 7.0,
      "neighborhood": "North Burnaby (Near SFU)",
      "address_text": "Approx map: 49.264000, -122.936900",
      "transit_minutes_to_ubc": 86
    },
    "craigslist_van:7934651062": {
      "url": "https://vancouver.craigslist.org/van/apa/d/vancouver-upper-level-bed-bath-house/7934651062.html",
      "title": "Upper Level 4 Bed / 3 Bath House with A/C in East Vancouver Hastings",
      "source": "craigslist_van",
      "price_cad": 4200,
      "bedrooms": 4.0,
      "neighborhood": "Vancouver",
      "address_text": "2723 Turner St, Vancouver, BC V5K2G8",
      "transit_minutes_to_ubc": 62
    },
    "craigslist_van:7927725239": {
      "url": "https://vancouver.craigslist.org/van/apa/d/vancouver-one-bedroom-available-now-in/7927725239.html",
      "title": "one bedroom available now in basement CLOSE TO UBC",
      "source": "craigslist_van",
      "price_cad": 1000,
      "bedrooms": 4.0,
      "neighborhood": "Alma st and W 10th AVE",
      "address_text": "Alma st, VANCOUVER, BC V6X0C3",
      "transit_minutes_to_ubc": 30
    },
    "craigslist_van:7934059479": {
      "url": "https://vancouver.craigslist.org/van/apa/d/vancouver-east-van-entire-house-for-rent/7934059479.html",
      "title": "East Van Entire House For Rent",
      "source": "craigslist_van",
      "price_cad": 4800,
      "bedrooms": 5.0,
      "neighborhood": "city of vancouver",
      "address_text": "E 55 Ave, Vancouver, BC V5P1Z4",
      "transit_minutes_to_ubc": 62
    },
    "craigslist_van:7927141037": {
      "url": "https://vancouver.craigslist.org/van/apa/d/vancouver-ground-floor-bedroom-bathroom/7927141037.html",
      "title": "Ground floor 4 bedroom 2 bathroom Vancouver 19th Ave near UBC LordByng",
      "source": "craigslist_van",
      "price_cad": 3900,
      "bedrooms": 4.0,
      "neighborhood": "34xxxx W 19th Ave Vancouver",
      "address_text": "Approx map: 49.255297, -123.180707",
      "transit_minutes_to_ubc": 30
    },
    "craigslist_van:7925235248": {
      "url": "https://vancouver.craigslist.org/van/apa/d/vancouver-basement-big-bedroom-bathroom/7925235248.html",
      "title": "Basement big 4 bedroom 2 bathroom near UBC 11th Ave Vancouver West",
      "source": "craigslist_van",
      "price_cad": 5200,
      "bedrooms": 4.0,
      "neighborhood": "43xxx W 11th Ave Vancouver",
      "address_text": "Approx map: 49.262590, -123.203773",
      "transit_minutes_to_ubc": 15
    },
    "craigslist_van:7933960538": {
      "url": "https://vancouver.craigslist.org/van/apa/d/vancouver-kerrisdale-bed-bath-character/7933960538.html",
      "title": "Kerrisdale 4 Bed 2 Bath Character House w/ Fenced Backyard",
      "source": "craigslist_van",
      "price_cad": 4500,
      "bedrooms": 4.0,
      "neighborhood": "Vancouver",
      "address_text": "5998 Larch Street, Vancouver, BC V6M4E4",
      "transit_minutes_to_ubc": 33
    },
    "craigslist_van:7934622616": {
      "url": "https://vancouver.craigslist.org/van/apa/d/vancouver-rooms-suite-in-vancouver-west/7934622616.html",
      "title": "5 rooms Suite in Vancouver West (Macdonald Street)",
      "source": "craigslist_van",
      "price_cad": 3200,
      "bedrooms": 5.0,
      "neighborhood": "Vancouver",
      "address_text": "Approx map: 49.249700, -123.166000",
      "transit_minutes_to_ubc": 23
    },
    "craigslist_van:7929517213": {
      "url": "https://vancouver.craigslist.org/van/apa/d/vancouver-executive-spacious-family/7929517213.html",
      "title": "Executive & Spacious Family Home Vancouver West Side",
      "source": "craigslist_van",
      "price_cad": 5199,
      "bedrooms": 5.0,
      "neighborhood": "Vancouver West \u2013Marpole Oakridge",
      "address_text": "W62 Ave, Vancouver, BC V6X2E4",
      "transit_minutes_to_ubc": 48
    },
    "craigslist_van:7930015480": {
      "url": "https://vancouver.craigslist.org/van/apa/d/delta-northeast-bedroom-bathroom-home/7930015480.html",
      "title": "5-bedroom, 3-bathroom home located Delta",
      "source": "craigslist_van",
      "price_cad": 4000,
      "bedrooms": 5.0,
      "neighborhood": "city of vancouver",
      "address_text": "Approx map: 49.155100, -122.912400",
      "transit_minutes_to_ubc": 106
    },
    "craigslist_van:7934529779": {
      "url": "https://vancouver.craigslist.org/van/apa/d/vancouver-4br-upper-suite-with-mountain/7934529779.html",
      "title": "4BR Upper Suite with Mountain View",
      "source": "craigslist_van",
      "price_cad": 4990,
      "bedrooms": 4.0,
      "neighborhood": "Vancouver",
      "address_text": "Arbutus, Vancouver, BC V6L2B2",
      "transit_minutes_to_ubc": 37
    },
    "craigslist_van:7925998985": {
      "url": "https://vancouver.craigslist.org/van/apa/d/vancouver-two-storeys-bed-bath-unit-in/7925998985.html",
      "title": "TWO STOREYS 4 BED & 2 BATH UNIT IN DESIRABLE MAIN",
      "source": "craigslist_van",
      "price_cad": 4900,
      "bedrooms": 4.0,
      "neighborhood": "Vancouver",
      "address_text": "Approx map: 49.248000, -123.091300",
      "transit_minutes_to_ubc": 52
    },
    "craigslist_van:7934514811": {
      "url": "https://vancouver.craigslist.org/van/apa/d/vancouver-luxury-family-home-for-rent/7934514811.html",
      "title": "Luxury Family Home for Rent \u2013 Vancouver",
      "source": "craigslist_van",
      "price_cad": 4800,
      "bedrooms": 5.0,
      "neighborhood": "Vancouver",
      "address_text": "3015 E 59th Ave,, Vancouver, BC V5S2B2",
      "transit_minutes_to_ubc": 58
    },
    "craigslist_van:7928323538": {
      "url": "https://vancouver.craigslist.org/van/apa/d/vancouver-bedroom-two-level-house-for/7928323538.html",
      "title": "4 BEDROOM TWO-LEVEL HOUSE FOR RENT",
      "source": "craigslist_van",
      "price_cad": 3300,
      "bedrooms": 4.0,
      "neighborhood": "Vancouver, Hastings Sunrise",
      "address_text": "Nanaimo, Vancouver, BC V5K2Y4",
      "transit_minutes_to_ubc": 72
    },
    "craigslist_van:7930221460": {
      "url": "https://vancouver.craigslist.org/van/apa/d/vancouver-vancouver-west-oak-street/7930221460.html",
      "title": "Vancouver West Oak Street 4 Bedrooms Townhouse",
      "source": "craigslist_van",
      "price_cad": 4700,
      "bedrooms": 4.0,
      "neighborhood": "city of vancouver",
      "address_text": "Approx map: 49.215100, -123.139600",
      "transit_minutes_to_ubc": 44
    },
    "craigslist_van:7934383313": {
      "url": "https://vancouver.craigslist.org/van/apa/d/vancouver-marpole-oakridge-townhouse/7934383313.html",
      "title": "Marpole Oakridge Townhouse 4 bdr 2.5 baths plus 1 den available now",
      "source": "craigslist_van",
      "price_cad": 5800,
      "bedrooms": 4.0,
      "neighborhood": "Vancouver",
      "address_text": "Approx map: 49.215600, -123.097900",
      "transit_minutes_to_ubc": 56
    },
    "craigslist_van:7932854567": {
      "url": "https://vancouver.craigslist.org/van/apa/d/vancouver-spacious-lot-single-house-at/7932854567.html",
      "title": "Spacious Lot Single House at Cambie Van",
      "source": "craigslist_van",
      "price_cad": 3800,
      "bedrooms": 4.0,
      "neighborhood": "city of vancouver",
      "address_text": "Approx map: 49.241026, -123.123361",
      "transit_minutes_to_ubc": 43
    },
    "craigslist_van:7934356069": {
      "url": "https://vancouver.craigslist.org/van/apa/d/delta-central-bedroom-entire-home-for/7934356069.html",
      "title": "4 bedroom entire home for rent",
      "source": "craigslist_van",
      "price_cad": 4495,
      "bedrooms": 4.0,
      "neighborhood": "Ladner",
      "address_text": "4982 57 A street, Delta Central, BC V4K3G5",
      "transit_minutes_to_ubc": 82
    },
    "craigslist_van:7934339012": {
      "url": "https://vancouver.craigslist.org/van/apa/d/vancouver-semi-furnished-bed-bath/7934339012.html",
      "title": "Semi-Furnished 5 Bed, 5 Bath PENTHOUSE @ PORTOFINO  in Downtown!",
      "source": "craigslist_van",
      "price_cad": 5995,
      "bedrooms": 5.0,
      "neighborhood": "Vancouver/Downtown Vancouver",
      "address_text": "1383 Howe Street, Vancouver, BC V6Z2R5",
      "transit_minutes_to_ubc": 41
    },
    "craigslist_van:7934277287": {
      "url": "https://vancouver.craigslist.org/van/apa/d/vancouver-spacious-bedroom-home-in/7934277287.html",
      "title": "Spacious 4-Bedroom Home in Prime Oakridge (One Month Free Rent)",
      "source": "craigslist_van",
      "price_cad": 4500,
      "bedrooms": 4.0,
      "neighborhood": "city of vancouver",
      "address_text": "Approx map: 49.229270, -123.107933",
      "transit_minutes_to_ubc": 48
    },
    "craigslist_van:7934273760": {
      "url": "https://vancouver.craigslist.org/van/apa/d/vancouver-spacious-bed-home-in-renfrew/7934273760.html",
      "title": "Spacious 4 Bed Home in Renfrew Heights \u2013 City & Mountain Views!",
      "source": "craigslist_van",
      "price_cad": 4600,
      "bedrooms": 4.0,
      "neighborhood": "Vancouver",
      "address_text": "Seaforth Dr, Vancouver, BC V5M4C5",
      "transit_minutes_to_ubc": 73
    },
    "craigslist_van:7933740455": {
      "url": "https://vancouver.craigslist.org/van/apa/d/vancouver-brand-new-br-ba-ac-laneway/7933740455.html",
      "title": "Brand New 5-BR 3-BA w AC laneway house | St George | UBC",
      "source": "craigslist_van",
      "price_cad": 6500,
      "bedrooms": 5.0,
      "neighborhood": "Vancouver",
      "address_text": "w 28, Vancouver, BC V6S1S7",
      "transit_minutes_to_ubc": 35
    },
    "craigslist_van:7932862052": {
      "url": "https://vancouver.craigslist.org/van/apa/d/vancouver-bedroom-floor-apartment-in/7932862052.html",
      "title": "5 Bedroom 2 Floor Apartment in DTES / Strathcona",
      "source": "craigslist_van",
      "price_cad": 2500,
      "bedrooms": 5.0,
      "neighborhood": "city of vancouver",
      "address_text": "Approx map: 49.277900, -123.090800",
      "transit_minutes_to_ubc": 62
    },
    "craigslist_van:7930035584": {
      "url": "https://vancouver.craigslist.org/van/apa/d/vancouver-close-to-ubc-spacious-single/7930035584.html",
      "title": "Close to UBC spacious single house 4Bdrm Basement",
      "source": "craigslist_van",
      "price_cad": 2650,
      "bedrooms": 4.0,
      "neighborhood": "Vancouver",
      "address_text": "28th ave, Vancouver, BC V6S1S8",
      "transit_minutes_to_ubc": 39
    },
    "craigslist_van:7931594367": {
      "url": "https://vancouver.craigslist.org/van/apa/d/vancouver-east-van-house-for-rent/7931594367.html",
      "title": "East Van House for Rent",
      "source": "craigslist_van",
      "price_cad": 4200,
      "bedrooms": 5.0,
      "neighborhood": "Vancouver",
      "address_text": "43rd ave, Vancouver, BC V5R2Z8",
      "transit_minutes_to_ubc": 55
    },
    "craigslist_van:7925726147": {
      "url": "https://vancouver.craigslist.org/van/apa/d/vancouver-bedrooms-upper-floor-house/7925726147.html",
      "title": "4 Bedrooms Upper Floor House for Rent 2262 Nanaimo Street & E 7th Ave",
      "source": "craigslist_van",
      "price_cad": 2500,
      "bedrooms": 4.0,
      "neighborhood": "Vancouver",
      "address_text": "2262 nanaimo street, Vancouver, BC V5N5C9",
      "transit_minutes_to_ubc": 55
    },
    "craigslist_van:7926826575": {
      "url": "https://vancouver.craigslist.org/van/apa/d/vancouver-unique-year-rental/7926826575.html",
      "title": "Unique 1 year rental opportunity:  4 bdrm View house in Dunbar",
      "source": "craigslist_van",
      "price_cad": 6250,
      "bedrooms": 4.0,
      "neighborhood": "Vancouver, Dunbar, Point Grey, Kitsilano, UBC, Westside",
      "address_text": "w 18th ave, Vancouver, BC V6S1A7",
      "transit_minutes_to_ubc": 28
    },
    "craigslist_van:7931101041": {
      "url": "https://vancouver.craigslist.org/van/apa/d/vancouver-4900-4br-bath-single-house/7931101041.html",
      "title": "$4900 /m 4br & 2 bath single house close to UBC",
      "source": "craigslist_van",
      "price_cad": 4900,
      "bedrooms": 4.0,
      "neighborhood": "w 16th Ave Vancouver",
      "address_text": "Approx map: 49.258521, -123.201950",
      "transit_minutes_to_ubc": 17
    },
    "craigslist_van:7932327305": {
      "url": "https://vancouver.craigslist.org/van/apa/d/vancouver-bedroom-bathroom-ground-floor/7932327305.html",
      "title": "\u2600 4 Bedroom, 1 Bathroom Ground Floor Rupert Skytrain Available June 1\u2600",
      "source": "craigslist_van",
      "price_cad": 3000,
      "bedrooms": 4.0,
      "neighborhood": "Rupert Station",
      "address_text": "Rupert, Vancouver, BC V5M2M5",
      "transit_minutes_to_ubc": 60
    },
    "craigslist_van:7934160673": {
      "url": "https://vancouver.craigslist.org/van/apa/d/surrey-spacious-or-5bedroom-upper-level/7934160673.html",
      "title": "Spacious 3 (or 5)Bedroom Upper-Level Home in Fleetwood, Surrey",
      "source": "craigslist_van",
      "price_cad": 3980,
      "bedrooms": 4.0,
      "neighborhood": "Fleetwood",
      "address_text": "Approx map: 49.155559, -122.769470",
      "transit_minutes_to_ubc": 118
    },
    "craigslist_van:7932391841": {
      "url": "https://vancouver.craigslist.org/van/apa/d/vancouver-rare-fraserview-rental-custom/7932391841.html",
      "title": "Rare Fraserview Rental \u2013 Custom-Built Luxury Home (7 Bed / 6 Bath)",
      "source": "craigslist_van",
      "price_cad": 6500,
      "bedrooms": 7.0,
      "neighborhood": "city of vancouver",
      "address_text": "Approx map: 49.222000, -123.068300",
      "transit_minutes_to_ubc": 58
    },
    "craigslist_van:7933390895": {
      "url": "https://vancouver.craigslist.org/van/apa/d/vancouver-bedroom-bathroom-living-room/7933390895.html",
      "title": "4 bedroom 2 bathroom 2 living room",
      "source": "craigslist_van",
      "price_cad": 3800,
      "bedrooms": 4.0,
      "neighborhood": "Vancouver",
      "address_text": "Approx map: 49.260000, -123.039800",
      "transit_minutes_to_ubc": 61
    },
    "craigslist_van:7934043714": {
      "url": "https://vancouver.craigslist.org/van/apa/d/surrey-east-large-home-with-separate/7934043714.html",
      "title": "Large Home with Separate Suite Near Schools, Parks & Shopping!",
      "source": "craigslist_van",
      "price_cad": 3800,
      "bedrooms": 4.0,
      "neighborhood": "Surrey, BC",
      "address_text": "57 Ave, Surrey, BC, BC V3S8W3",
      "transit_minutes_to_ubc": 136
    },
    "craigslist_van:7928453208": {
      "url": "https://vancouver.craigslist.org/van/apa/d/burnaby-bedroom-25-bathroom-house-for/7928453208.html",
      "title": "6 bedroom/2.5 bathroom house for rent",
      "source": "craigslist_van",
      "price_cad": 4300,
      "bedrooms": 6.0,
      "neighborhood": "Burnaby",
      "address_text": "7765 Allman Street, Burnaby, BC V5E2A9",
      "transit_minutes_to_ubc": 95
    },
    "craigslist_van:7932996775": {
      "url": "https://vancouver.craigslist.org/van/apa/d/vancouver-cozy-family-bedrooms-home/7932996775.html",
      "title": "Cozy Family 5 Bedrooms Home",
      "source": "craigslist_van",
      "price_cad": 6200,
      "bedrooms": 5.0,
      "neighborhood": "Mackenzie Heights",
      "address_text": "3259 W35 Avenue, Vancouver, BC V6N2M9",
      "transit_minutes_to_ubc": 35
    },
    "craigslist_van:7926291709": {
      "url": "https://vancouver.craigslist.org/van/apa/d/vancouver-viewings-tonight-thursday-may/7926291709.html",
      "title": "Viewings tonight! Thursday May 14 - House near Trout Lake/CommercialDr",
      "source": "craigslist_van",
      "price_cad": 985,
      "bedrooms": 4.0,
      "neighborhood": "Commercial Drive",
      "address_text": "Approx map: 49.255100, -123.066700",
      "transit_minutes_to_ubc": 64
    },
    "craigslist_van:7933847250": {
      "url": "https://vancouver.craigslist.org/van/apa/d/vancouver-warning-brand-new-house-for/7933847250.html",
      "title": "WARNING! Brand new house for rent Beside PNE LONG/SHORT TERM RENTAL",
      "source": "craigslist_van",
      "price_cad": 6000,
      "bedrooms": 4.0,
      "neighborhood": "Vancouver",
      "address_text": "renfrew, vancouver, BC V5K4A7",
      "transit_minutes_to_ubc": 73
    },
    "craigslist_van:7932891790": {
      "url": "https://vancouver.craigslist.org/van/apa/d/vancouver-brand-new-house-in-vancouver/7932891790.html",
      "title": "Brand New House in Vancouver / Vacation & Short-Term Rental Options",
      "source": "craigslist_van",
      "price_cad": 120,
      "bedrooms": 4.0,
      "neighborhood": "Vancouver",
      "address_text": "Knight Street, Vancouver, BC V5W3N3",
      "transit_minutes_to_ubc": 43
    },
    "craigslist_van:7933668906": {
      "url": "https://vancouver.craigslist.org/van/apa/d/vancouver-house-east-vancouver-great/7933668906.html",
      "title": "House EAST VANCOUVER Great Location 5bd+2bth+yard+parking NOW/JUNE 1",
      "source": "craigslist_van",
      "price_cad": 3200,
      "bedrooms": 5.0,
      "neighborhood": "city of vancouver",
      "address_text": "1st Avenue, Vancouver, BC V5M1A2",
      "transit_minutes_to_ubc": 76
    },
    "craigslist_van:7927399350": {
      "url": "https://vancouver.craigslist.org/van/apa/d/vancouver-bedroom-suite-near-ubc/7927399350.html",
      "title": "4-bedroom suite near UBC",
      "source": "craigslist_van",
      "price_cad": 1200,
      "bedrooms": 4.0,
      "neighborhood": "Vancouver West",
      "address_text": "SW Marine Drive, Vancouver, BC V6N1Y4",
      "transit_minutes_to_ubc": 43
    },
    "craigslist_van:7927399279": {
      "url": "https://vancouver.craigslist.org/van/apa/d/vancouver-bedroom-bathroom-student/7927399279.html",
      "title": "4-bedroom 2-bathroom student housing",
      "source": "craigslist_van",
      "price_cad": 1150,
      "bedrooms": 4.0,
      "neighborhood": "Vancouver West",
      "address_text": "Approx map: 49.234727, -123.194675",
      "transit_minutes_to_ubc": 21
    },
    "craigslist_van:7925953279": {
      "url": "https://vancouver.craigslist.org/van/apa/d/vancouver-bargain/7925953279.html",
      "title": "**BARGAIN**",
      "source": "craigslist_van",
      "price_cad": 3500,
      "bedrooms": 5.0,
      "neighborhood": "VANCOUVER",
      "address_text": "1257 E 18TH AVE, Vancouver, BC V5V1H3",
      "transit_minutes_to_ubc": 61
    },
    "craigslist_van:7933564248": {
      "url": "https://vancouver.craigslist.org/van/apa/d/vancouver-coastal-luxury-with-zen/7933564248.html",
      "title": "Coastal Luxury with Zen Tranquility",
      "source": "craigslist_van",
      "price_cad": 3895,
      "bedrooms": 4.0,
      "neighborhood": "Vancouver",
      "address_text": "4150 W 8th Ave, Vancouver, BC V6R1Z6",
      "transit_minutes_to_ubc": 24
    },
    "craigslist_van:7933487579": {
      "url": "https://vancouver.craigslist.org/van/apa/d/vancouver-bedroom-level-townhouse-on/7933487579.html",
      "title": "4-bedroom, 3-level townhouse on UBC campus available June 1st",
      "source": "craigslist_van",
      "price_cad": 5300,
      "bedrooms": 4.0,
      "neighborhood": "UBC Campus",
      "address_text": "Kings Rd, Vancouver, BC V6T1K8",
      "transit_minutes_to_ubc": 10
    },
    "craigslist_van:7933480889": {
      "url": "https://vancouver.craigslist.org/van/apa/d/vancouver-fairly-new-bed-bath-vancouver/7933480889.html",
      "title": "Fairly new 4 bed, 3 bath Vancouver family home for Rent",
      "source": "craigslist_van",
      "price_cad": 4800,
      "bedrooms": 4.0,
      "neighborhood": "city of vancouver",
      "address_text": "4870 Ross, Vancouver, BC V5V4V2",
      "transit_minutes_to_ubc": 55
    },
    "craigslist_van:7933480451": {
      "url": "https://vancouver.craigslist.org/van/apa/d/vancouver-fully-furnished-spacious-4bd/7933480451.html",
      "title": "Fully-furnished spacious 4BD upper-level house next to UBC for 4-5",
      "source": "craigslist_van",
      "price_cad": 5000,
      "bedrooms": 4.0,
      "neighborhood": "city of vancouver",
      "address_text": "Approx map: 49.266600, -123.197600",
      "transit_minutes_to_ubc": 21
    },
    "craigslist_van:7932644110": {
      "url": "https://vancouver.craigslist.org/van/apa/d/vancouver-fully-furnished-arbutus-whole/7932644110.html",
      "title": "Fully Furnished Arbutus Whole House",
      "source": "craigslist_van",
      "price_cad": 6000,
      "bedrooms": 7.0,
      "neighborhood": "Burnaby, BC, UBC",
      "address_text": "2429 McBain Ave, Vancouver, BC, BC V6L2C5",
      "transit_minutes_to_ubc": 35
    },
    "craigslist_van:7929260796": {
      "url": "https://vancouver.craigslist.org/van/apa/d/vancouver-private-rooms-for-rent-ubc/7929260796.html",
      "title": "Private Rooms for Rent UBC, Dunbar",
      "source": "craigslist_van",
      "price_cad": 1050,
      "bedrooms": 5.0,
      "neighborhood": "UBC, Dunbar, Southlands, Kerrisdale",
      "address_text": "Holland Street, Vancouver, BC V6N2A7",
      "transit_minutes_to_ubc": 21
    },
    "craigslist_van:7930400210": {
      "url": "https://vancouver.craigslist.org/van/apa/d/vancouver-5bed-5ba-whole-house-in-south/7930400210.html",
      "title": "5BED/5BA Whole house in South Granville",
      "source": "craigslist_van",
      "price_cad": 5800,
      "bedrooms": 5.0,
      "neighborhood": "South Granville",
      "address_text": "W 48th Ave, Vancouver, BC V6M2N5",
      "transit_minutes_to_ubc": 35
    },
    "craigslist_van:7933327831": {
      "url": "https://vancouver.craigslist.org/van/apa/d/vancouver-near-transit-endless-hot/7933327831.html",
      "title": "Near Transit Endless hot water high-efficient system Downtown 13 minut",
      "source": "craigslist_van",
      "price_cad": 3800,
      "bedrooms": 4.0,
      "neighborhood": "Mount Pleasant",
      "address_text": "E 12th Ave, Vancouver, BC V5T2H8",
      "transit_minutes_to_ubc": 49
    },
    "craigslist_van:7933308368": {
      "url": "https://vancouver.craigslist.org/van/apa/d/vancouver-long-term-or-short-term-near/7933308368.html",
      "title": "LONG term OR SHORT Term near SkyTrain Furnished or Unfurnished #9",
      "source": "craigslist_van",
      "price_cad": 4509,
      "bedrooms": 5.0,
      "neighborhood": "SkyTrain",
      "address_text": "E 14th Ave, Vancouver, BC V5M2J5",
      "transit_minutes_to_ubc": 67
    },
    "craigslist_van:7926865173": {
      "url": "https://vancouver.craigslist.org/van/apa/d/vancouver-bed-bath-house-upper-suite/7926865173.html",
      "title": "4 Bed 2 Bath House Upper Suite Fraserview Vancouver East",
      "source": "craigslist_van",
      "price_cad": 3600,
      "bedrooms": 4.0,
      "neighborhood": "Fraserview",
      "address_text": "Approx map: 49.209044, -123.059235",
      "transit_minutes_to_ubc": 69
    },
    "craigslist_van:7925509096": {
      "url": "https://vancouver.craigslist.org/van/apa/d/vancouver-special-offer-6000-month-for/7925509096.html",
      "title": "Special offer: $6000 /Month for 5 Bedroom  Luxury House  in Vancouver",
      "source": "craigslist_van",
      "price_cad": 6000,
      "bedrooms": 5.0,
      "neighborhood": "Oakridge",
      "address_text": "1339 West 53rd Ave, Vancouver, BC V6P1K8",
      "transit_minutes_to_ubc": 41
    },
    "craigslist_van:7933128698": {
      "url": "https://vancouver.craigslist.org/van/apa/d/vancouver-room-for-rent/7933128698.html",
      "title": "Room for rent",
      "source": "craigslist_van",
      "price_cad": 1000,
      "bedrooms": 4.0,
      "neighborhood": "Vancouver",
      "address_text": "2690 trinity street, Vancouver, BC V5K1H2",
      "transit_minutes_to_ubc": 72
    },
    "craigslist_van:7933128677": {
      "url": "https://vancouver.craigslist.org/van/apa/d/vancouver-vancouver-south-bedroom-bath/7933128677.html",
      "title": "VANCOUVER SOUTH 4 BEDROOM 2 BATH SUITE",
      "source": "craigslist_van",
      "price_cad": 3200,
      "bedrooms": 4.0,
      "neighborhood": "VANCOUVER",
      "address_text": "EAST 63 AVE, VANCOUVER, BC V5X2K7",
      "transit_minutes_to_ubc": 60
    },
    "craigslist_van:7932157524": {
      "url": "https://vancouver.craigslist.org/van/apa/d/vancouver-furnished-kitsilano-4br/7932157524.html",
      "title": "Furnished Kitsilano 4BR Laneway w/utilities, near #99 UBC Express Bus",
      "source": "craigslist_van",
      "price_cad": 4800,
      "bedrooms": 4.0,
      "neighborhood": "city of vancouver",
      "address_text": "Dunbar Street, Vancouver, BC V6R2G3",
      "transit_minutes_to_ubc": 18
    },
    "craigslist_van:7924980326": {
      "url": "https://vancouver.craigslist.org/van/apa/d/vancouver-level-renovated-townhouse-in/7924980326.html",
      "title": "3 level Renovated townhouse in Marpole area",
      "source": "craigslist_van",
      "price_cad": 5000,
      "bedrooms": 4.0,
      "neighborhood": "Oak St and W.59 Ave",
      "address_text": "985 Westbury Walk, Vancouver, BC V6P6Z5",
      "transit_minutes_to_ubc": 46
    },
    "craigslist_van:7930518372": {
      "url": "https://vancouver.craigslist.org/van/apa/d/vancouver-br-unit-for-rent/7930518372.html",
      "title": "$3913.00 / 4BR Unit for Rent",
      "source": "craigslist_van",
      "price_cad": 3913,
      "bedrooms": 4.0,
      "neighborhood": "Vancouver",
      "address_text": "122 Walter Hardwick Ave, vancouver, BC V5Y0C9",
      "transit_minutes_to_ubc": 38
    },
    "craigslist_van:7933051506": {
      "url": "https://vancouver.craigslist.org/van/apa/d/vancouver-4br-25ba-vancouver-west/7933051506.html",
      "title": "4BR / 2.5BA Vancouver West Townhouse Near Oakridge",
      "source": "craigslist_van",
      "price_cad": 5300,
      "bedrooms": 4.0,
      "neighborhood": "Oakridge",
      "address_text": "Ash Street, Vancouver, BC V5Z3G9",
      "transit_minutes_to_ubc": 39
    },
    "craigslist_van:7933004141": {
      "url": "https://vancouver.craigslist.org/van/apa/d/vancouver-sept1-bright-newer-br-garden/7933004141.html",
      "title": "Sept.1 - Bright Newer 4 Br. Garden Suite in Prime Dunbar",
      "source": "craigslist_van",
      "price_cad": 4190,
      "bedrooms": 4.0,
      "neighborhood": "Dunbar, Vancouver",
      "address_text": "Highbury St., Vancouver, BC V6L2V9",
      "transit_minutes_to_ubc": 28
    },
    "craigslist_van:7932896720": {
      "url": "https://vancouver.craigslist.org/van/apa/d/vancouver-br-brand-new-renovation/7932896720.html",
      "title": "$3,600 4 br BRAND NEW RENOVATION VANCOUVER 2nd floor with a big Patio",
      "source": "craigslist_van",
      "price_cad": 3600,
      "bedrooms": 4.0,
      "neighborhood": "vancouver",
      "address_text": "5274 Taunton Street, Vancouver, BC V5R4B3",
      "transit_minutes_to_ubc": 58
    },
    "craigslist_van:7932725808": {
      "url": "https://vancouver.craigslist.org/van/apa/d/vancouver-featuring-private-gym-theater/7932725808.html",
      "title": "Featuring Private Gym, Theater & Golf Training Facility",
      "source": "craigslist_van",
      "price_cad": 3850,
      "bedrooms": 4.0,
      "neighborhood": "Vancouver",
      "address_text": "3233 SW Marine Dr, Vancouver, BC V6N3Y7",
      "transit_minutes_to_ubc": 27
    },
    "craigslist_van:7932671497": {
      "url": "https://vancouver.craigslist.org/van/apa/d/vancouver-entire-house-bedrooms-by/7932671497.html",
      "title": "Entire House 6 Bedrooms By Canada Line Station",
      "source": "craigslist_van",
      "price_cad": 4550,
      "bedrooms": 6.0,
      "neighborhood": "Vancouver,Canada Line, Cambie",
      "address_text": "Approx map: 49.247500, -123.121000",
      "transit_minutes_to_ubc": 44
    },
    "craigslist_van:7932450603": {
      "url": "https://vancouver.craigslist.org/van/apa/d/vancouver-shaughnessy-character-house/7932450603.html",
      "title": "Shaughnessy character house Upper 2 floors or whole house PRIME Locati",
      "source": "craigslist_van",
      "price_cad": 6595,
      "bedrooms": 7.0,
      "neighborhood": "Shaughnessy",
      "address_text": "Approx map: 49.257834, -123.185406",
      "transit_minutes_to_ubc": 23
    },
    "craigslist_van:7932442041": {
      "url": "https://vancouver.craigslist.org/van/apa/d/vancouver-move-in-ready-bedroom-house/7932442041.html",
      "title": "MOVE IN READY 4 bedroom house for rent in Oakridge Area",
      "source": "craigslist_van",
      "price_cad": 4500,
      "bedrooms": 4.0,
      "neighborhood": "Vancouver",
      "address_text": "ontario, Vancouver, BC V5Y2V9",
      "transit_minutes_to_ubc": 50
    },
    "craigslist_van:7930801532": {
      "url": "https://vancouver.craigslist.org/van/apa/d/vancouver-available-now-bedrooms-house/7930801532.html",
      "title": "Available NOW 4 bedrooms house for rent in Oakridge Area",
      "source": "craigslist_van",
      "price_cad": 4500,
      "bedrooms": 4.0,
      "neighborhood": "Vancouver",
      "address_text": "W48th Avenue, Vancouver, BC V5Y2V9",
      "transit_minutes_to_ubc": 29
    },
    "craigslist_van:7932383707": {
      "url": "https://vancouver.craigslist.org/van/apa/d/vancouver-mount-pleasant-half-duplex/7932383707.html",
      "title": "Mount Pleasant - Half Duplex | 4 bed/4 bath | Avail June 15 or July 1",
      "source": "craigslist_van",
      "price_cad": 6000,
      "bedrooms": 4.0,
      "neighborhood": "Mount Pleasant",
      "address_text": "Approx map: 49.262000, -123.092300",
      "transit_minutes_to_ubc": 46
    },
    "craigslist_van:7932368554": {
      "url": "https://vancouver.craigslist.org/van/apa/d/vancouver-van-east-house-for-rent/7932368554.html",
      "title": "Van East House for Rent",
      "source": "craigslist_van",
      "price_cad": 4400,
      "bedrooms": 5.0,
      "neighborhood": "Vancouver",
      "address_text": "Approx map: 49.226423, -123.042412",
      "transit_minutes_to_ubc": 65
    },
    "craigslist_van:7932151174": {
      "url": "https://vancouver.craigslist.org/van/apa/d/vancouver-bed-bath-family-home-for-rent/7932151174.html",
      "title": "4 Bed / 4 Bath Family Home for Rent \u2013 East Vancouver",
      "source": "craigslist_van",
      "price_cad": 5800,
      "bedrooms": 4.0,
      "neighborhood": "Main/Fraser",
      "address_text": "Approx map: 49.232700, -123.091700",
      "transit_minutes_to_ubc": 41
    },
    "craigslist_van:7929688454": {
      "url": "https://vancouver.craigslist.org/van/apa/d/langley-township-northwest-bed-35-bath/7929688454.html",
      "title": "\ud83c\udfe1 4 Bed + 3.5 Bath Townhouse for Rent \u2013 Willoughby area Langley",
      "source": "craigslist_van",
      "price_cad": 3800,
      "bedrooms": 4.0,
      "neighborhood": "Willoughby",
      "address_text": "80 Avenue, Langley, BC V2Y0J4",
      "transit_minutes_to_ubc": 127
    },
    "craigslist_van:7931993631": {
      "url": "https://vancouver.craigslist.org/van/apa/d/vancouver-bright-bedroom-character/7931993631.html",
      "title": "Bright 4-bedroom character duplex near VGH with sunny gardens",
      "source": "craigslist_van",
      "price_cad": 5200,
      "bedrooms": 4.0,
      "neighborhood": "Vancouver",
      "address_text": "Approx map: 49.257274, -123.123436",
      "transit_minutes_to_ubc": 40
    },
    "craigslist_van:7931993532": {
      "url": "https://vancouver.craigslist.org/van/apa/d/west-vancouver-luxury-mega-mansion/7931993532.html",
      "title": "Luxury mega mansion",
      "source": "craigslist_van",
      "price_cad": 3000,
      "bedrooms": 5.0,
      "neighborhood": "West Vancouver",
      "address_text": "Approx map: 49.461400, -123.329400",
      "transit_minutes_to_ubc": null
    },
    "craigslist_van:7929962128": {
      "url": "https://vancouver.craigslist.org/van/apa/d/vancouver-new-built-duplex-house-bed/7929962128.html",
      "title": "New built Duplex house 4 bed room4 bathroom for rent",
      "source": "craigslist_van",
      "price_cad": 5500,
      "bedrooms": 4.0,
      "neighborhood": "Vancouver west",
      "address_text": "Approx map: 49.249100, -123.208800",
      "transit_minutes_to_ubc": 35
    },
    "padmapper:64223378": {
      "url": "https://www.padmapper.com/rentals/28423702p/4-bedroom-2-bath-apartment-at-82-west-45th-avenue-vancouver-bc-v5y-2v9",
      "title": null,
      "source": "padmapper",
      "price_cad": 4500,
      "bedrooms": 4.0,
      "neighborhood": "Oakridge",
      "address_text": "82 West 45th Avenue, Vancouver, BC, V5Y 2V9",
      "transit_minutes_to_ubc": 49
    },
    "padmapper:64355402": {
      "url": "https://www.padmapper.com/rentals/28499481p/4-bedroom-2-bath-apartment-at-7545-yukon-street-vancouver-bc-v5x-2y4",
      "title": null,
      "source": "padmapper",
      "price_cad": 5800,
      "bedrooms": 4.0,
      "neighborhood": "Marpole",
      "address_text": "7545 Yukon Street, Vancouver, BC, V5X 2Y4",
      "transit_minutes_to_ubc": 52
    },
    "padmapper:59887444": {
      "url": "https://www.padmapper.com/rentals/28177301p/4-bedroom-2-bath-apartment-at-4359-main-street-vancouver-bc-v5v-3r1",
      "title": null,
      "source": "padmapper",
      "price_cad": 4900,
      "bedrooms": 4.0,
      "neighborhood": "Riley Park - Little Mountain",
      "address_text": "4359 Main Street, Vancouver, BC, V5V 3R1",
      "transit_minutes_to_ubc": 50
    },
    "padmapper:63622948": {
      "url": "https://www.padmapper.com/rentals/28514222p/4-bedroom-1-bath-apartment-at-e-6th-ave-nanaimo-st-vancouver-bc-v5n-5c7",
      "title": null,
      "source": "padmapper",
      "price_cad": 2999,
      "bedrooms": 4.0,
      "neighborhood": "Grandview-Woodland",
      "address_text": "E 6th Ave & Nanaimo St, Vancouver, BC, V5N 5C7",
      "transit_minutes_to_ubc": 55
    },
    "padmapper:64366068": {
      "url": "https://www.padmapper.com/rentals/64366068/4-bedroom-3-bath-apartment-at-2723-turner-street-vancouver-bc-v5k-2g3",
      "title": null,
      "source": "padmapper",
      "price_cad": 4200,
      "bedrooms": 4.0,
      "neighborhood": "Hastings-Sunrise",
      "address_text": "2723 Turner Street, Vancouver, BC, V5K 2G3",
      "transit_minutes_to_ubc": 62
    },
    "padmapper:64354760": {
      "url": "https://www.padmapper.com/rentals/64354760/5-bedroom-5-bath-apartment-at-1383-howe-street-vancouver-bc-v6z-2r5",
      "title": null,
      "source": "padmapper",
      "price_cad": 5995,
      "bedrooms": 5.0,
      "neighborhood": "Downtown Vancouver",
      "address_text": "1383 Howe Street #PH, Vancouver, BC, V6Z 2R5",
      "transit_minutes_to_ubc": 41
    },
    "padmapper:64319285": {
      "url": "https://www.padmapper.com/rentals/64319285/4-bedroom-1-bath-apartment-at-w-8th-ave-tolmie-st-vancouver-bc-v6r-2a4",
      "title": null,
      "source": "padmapper",
      "price_cad": 5000,
      "bedrooms": 4.0,
      "neighborhood": "West Point Grey",
      "address_text": "W 8th Ave & Tolmie St, Vancouver, BC, V6R 2A4",
      "transit_minutes_to_ubc": 13
    },
    "padmapper:64310024": {
      "url": "https://www.padmapper.com/rentals/64310024/4-bedroom-2-bath-apartment-at-4285-st-george-st-vancouver-bc-v5v-4a3",
      "title": null,
      "source": "padmapper",
      "price_cad": 5400,
      "bedrooms": 4.0,
      "neighborhood": "Riley Park - Little Mountain",
      "address_text": "4285 St George St, Vancouver, BC, V5V 4A3",
      "transit_minutes_to_ubc": 52
    },
    "padmapper:62284509": {
      "url": "https://www.padmapper.com/rentals/62284509/5-bedroom-3-bath-apartment-at-camosun-st-w-28th-ave-vancouver-bc-v6s-1s8",
      "title": null,
      "source": "padmapper",
      "price_cad": 6500,
      "bedrooms": 5.0,
      "neighborhood": "Dunbar",
      "address_text": "Camosun St & W 28th Ave, Vancouver, BC, V6S 1S8",
      "transit_minutes_to_ubc": 34
    },
    "padmapper:64087176": {
      "url": "https://www.padmapper.com/rentals/64087176/4-bedroom-2-bath-apartment-at-2300-harrison-drive-vancouver-bc-v5p-2p8",
      "title": null,
      "source": "padmapper",
      "price_cad": 3800,
      "bedrooms": 4.0,
      "neighborhood": "Victoria-Fraserview",
      "address_text": "2300 Harrison Drive, Vancouver, BC, V5P 2P8",
      "transit_minutes_to_ubc": 68
    },
    "padmapper:64039717": {
      "url": "https://www.padmapper.com/rentals/64039717/5-bedroom-2-bath-apartment-at-4615-west-4th-avenue-vancouver-bc-v6r-1r6",
      "title": null,
      "source": "padmapper",
      "price_cad": 1125,
      "bedrooms": 5.0,
      "neighborhood": "West Point Grey",
      "address_text": "4615 West 4th Avenue, Vancouver, BC, V6R 1R6",
      "transit_minutes_to_ubc": 15
    },
    "rentals_ca:cmVudGFsbGlzdGluZzoxMTQxMzUy": {
      "url": "https://rentals.ca/vancouver/arbutus-ridge-id1141352",
      "title": null,
      "source": "rentals_ca",
      "price_cad": 1400,
      "bedrooms": 5.0,
      "neighborhood": null,
      "address_text": "Arbutus - Ridge, Vancouver, BC, V6N 1B2",
      "transit_minutes_to_ubc": 33
    },
    "rentals_ca:cmVudGFsbGlzdGluZzoxMDMzMjEw": {
      "url": "https://rentals.ca/vancouver/shaughnessy-id1033210",
      "title": null,
      "source": "rentals_ca",
      "price_cad": 2700,
      "bedrooms": 8.0,
      "neighborhood": null,
      "address_text": "Shaughnessy, Vancouver, BC, V6H 3K5",
      "transit_minutes_to_ubc": 36
    },
    "rentals_ca:cmVudGFsbGlzdGluZzoxMTAwNDUx": {
      "url": "https://rentals.ca/vancouver/sunset-id1100451",
      "title": "East 52nd Avenue",
      "source": "rentals_ca",
      "price_cad": 850,
      "bedrooms": 5.0,
      "neighborhood": null,
      "address_text": "East 52nd Avenue, Vancouver, BC, V5X 1G9",
      "transit_minutes_to_ubc": 53
    },
    "rentals_ca:cmVudGFsbGlzdGluZzoxMTc4MTI5": {
      "url": "https://rentals.ca/vancouver/roomies-1178129",
      "title": null,
      "source": "rentals_ca",
      "price_cad": 950,
      "bedrooms": 5.0,
      "neighborhood": null,
      "address_text": "Downtown, Vancouver, BC, V6A 1N4",
      "transit_minutes_to_ubc": 53
    },
    "rentals_ca:cmVudGFsbGlzdGluZzoxMzU4ODE2": {
      "url": "https://rentals.ca/vancouver/roomies-1358816",
      "title": "Nautilus Close",
      "source": "rentals_ca",
      "price_cad": 1200,
      "bedrooms": 6.0,
      "neighborhood": null,
      "address_text": "Nautilus Close, Vancouver, BC, V6R 4L2",
      "transit_minutes_to_ubc": 18
    },
    "rentals_ca:cmVudGFsbGlzdGluZzoxMDU5Nzc2": {
      "url": "https://rentals.ca/vancouver/walker-street-id1059776",
      "title": "Walker Street",
      "source": "rentals_ca",
      "price_cad": 1200,
      "bedrooms": 4.0,
      "neighborhood": null,
      "address_text": "Walker Street, Vancouver, BC, V5N 5A9",
      "transit_minutes_to_ubc": 64
    },
    "rentals_ca:cmVudGFsbGlzdGluZzoxMTk0ODYy": {
      "url": "https://rentals.ca/vancouver/roomies-1194862",
      "title": null,
      "source": "rentals_ca",
      "price_cad": 870,
      "bedrooms": 4.0,
      "neighborhood": null,
      "address_text": "Marpole, Vancouver, BC, V6P 4B2",
      "transit_minutes_to_ubc": 49
    },
    "rentals_ca:cmVudGFsbGlzdGluZzo5NjczMTE=": {
      "url": "https://rentals.ca/vancouver/east-21st-avenue-id967311",
      "title": "East 21st Avenue",
      "source": "rentals_ca",
      "price_cad": 985,
      "bedrooms": 5.0,
      "neighborhood": null,
      "address_text": "East 21st Avenue, Vancouver, BC",
      "transit_minutes_to_ubc": 62
    },
    "rentals_ca:cmVudGFsbGlzdGluZzoxMDU3NTYx": {
      "url": "https://rentals.ca/vancouver/sunset-id1057561",
      "title": null,
      "source": "rentals_ca",
      "price_cad": 900,
      "bedrooms": 4.0,
      "neighborhood": null,
      "address_text": "Sunset, Vancouver, BC, V5W 2P3",
      "transit_minutes_to_ubc": 43
    },
    "rentals_ca:cmVudGFsbGlzdGluZzoxMDkwNzMw": {
      "url": "https://rentals.ca/vancouver/east-61st-avenue-id1090730",
      "title": "East 61st Avenue",
      "source": "rentals_ca",
      "price_cad": 820,
      "bedrooms": 4.0,
      "neighborhood": null,
      "address_text": "East 61st Avenue, Vancouver, BC, V5X 2B7",
      "transit_minutes_to_ubc": 55
    },
    "rentals_ca:cmVudGFsbGlzdGluZzoxMTgyMDY0": {
      "url": "https://rentals.ca/vancouver/roomies-1182064",
      "title": "Oak Street",
      "source": "rentals_ca",
      "price_cad": 870,
      "bedrooms": 4.0,
      "neighborhood": null,
      "address_text": "Oak Street, Vancouver, BC, V6P 4B2",
      "transit_minutes_to_ubc": 54
    },
    "rentals_ca:cmVudGFsbGlzdGluZzoxMTU4ODEx": {
      "url": "https://rentals.ca/vancouver/roomies-1158811",
      "title": "West 28th Avenue",
      "source": "rentals_ca",
      "price_cad": 920,
      "bedrooms": 4.0,
      "neighborhood": null,
      "address_text": "Riley Park, Vancouver, BC, V5Y 2K7",
      "transit_minutes_to_ubc": 50
    },
    "rentals_ca:cmVudGFsbGlzdGluZzo5MTM0NTM=": {
      "url": "https://rentals.ca/vancouver/west-georgia-street-id913453",
      "title": "West Georgia Street",
      "source": "rentals_ca",
      "price_cad": 1700,
      "bedrooms": 4.0,
      "neighborhood": null,
      "address_text": "West Georgia Street, Vancouver, BC, V6G 3K4",
      "transit_minutes_to_ubc": 41
    },
    "rentals_ca:cmVudGFsbGlzdGluZzoxMDExNzY5": {
      "url": "https://rentals.ca/vancouver/marpole-id1011769",
      "title": null,
      "source": "rentals_ca",
      "price_cad": 1000,
      "bedrooms": 5.0,
      "neighborhood": null,
      "address_text": "Marpole, Vancouver, BC, V5X 2H8",
      "transit_minutes_to_ubc": 54
    },
    "rentals_ca:cmVudGFsbGlzdGluZzoxMTA4MjMy": {
      "url": "https://rentals.ca/vancouver/east-61st-avenue-id1108232",
      "title": "East 61st Avenue",
      "source": "rentals_ca",
      "price_cad": 820,
      "bedrooms": 4.0,
      "neighborhood": null,
      "address_text": "East 61st Avenue, Vancouver, BC, V5P 2K3",
      "transit_minutes_to_ubc": 61
    },
    "rentals_ca:cmVudGFsbGlzdGluZzoxMTg4Mzkx": {
      "url": "https://rentals.ca/vancouver/136-east-55th-avenue",
      "title": null,
      "source": "rentals_ca",
      "price_cad": 1000,
      "bedrooms": 4.0,
      "neighborhood": null,
      "address_text": "136 East 55th Avenue, Vancouver, BC, V5X 1M8",
      "transit_minutes_to_ubc": 51
    },
    "rentals_ca:cmVudGFsbGlzdGluZzoxMTk4NDIy": {
      "url": "https://rentals.ca/vancouver/2683-w-41st-ave",
      "title": "2683 W 41ST AVE",
      "source": "rentals_ca",
      "price_cad": 6000,
      "bedrooms": 4.0,
      "neighborhood": null,
      "address_text": "2683 W 41ST AVE, Vancouver, BC, V6N 3C3",
      "transit_minutes_to_ubc": 30
    },
    "rentals_ca:cmVudGFsbGlzdGluZzoxMDE0MTg5": {
      "url": "https://rentals.ca/vancouver/cambie-street-id1014189",
      "title": "Cambie Street",
      "source": "rentals_ca",
      "price_cad": 2500,
      "bedrooms": 4.0,
      "neighborhood": null,
      "address_text": "Cambie Street, Vancouver, BC, V6B 5X5",
      "transit_minutes_to_ubc": 50
    },
    "rentals_ca:cmVudGFsbGlzdGluZzoxMTAzNzkx": {
      "url": "https://rentals.ca/vancouver/58-w-ave",
      "title": "58 W Ave",
      "source": "rentals_ca",
      "price_cad": 900,
      "bedrooms": 5.0,
      "neighborhood": null,
      "address_text": "58 W Ave, Vancouver, BC, V6P 1W5",
      "transit_minutes_to_ubc": 63
    },
    "rentals_ca:cmVudGFsbGlzdGluZzoxMzYzMTQ4": {
      "url": "https://rentals.ca/vancouver/4870-ross-street",
      "title": null,
      "source": "rentals_ca",
      "price_cad": 4800,
      "bedrooms": 4.0,
      "neighborhood": null,
      "address_text": "4870 Ross Street, Vancouver, BC, V5V 4V2",
      "transit_minutes_to_ubc": 55
    },
    "rentals_ca:cmVudGFsbGlzdGluZzoxMTk2NzA4": {
      "url": "https://rentals.ca/vancouver/2019-east-45th-avenue",
      "title": null,
      "source": "rentals_ca",
      "price_cad": 3150,
      "bedrooms": 4.0,
      "neighborhood": null,
      "address_text": "2019 East 45th Avenue #3, Vancouver, BC, V5P 1N7",
      "transit_minutes_to_ubc": 49
    },
    "rentals_ca:cmVudGFsbGlzdGluZzoxMTk2OTQ5": {
      "url": "https://rentals.ca/vancouver/roomies-1196949",
      "title": "East 8th Avenue",
      "source": "rentals_ca",
      "price_cad": 1100,
      "bedrooms": 5.0,
      "neighborhood": null,
      "address_text": "East 8th Avenue, Vancouver, BC, V5M 1X2",
      "transit_minutes_to_ubc": 57
    },
    "rentals_ca:cmVudGFsbGlzdGluZzoxMjA1NDA1": {
      "url": "https://rentals.ca/vancouver/roomies-1205405",
      "title": "East 24th Avenue",
      "source": "rentals_ca",
      "price_cad": 900,
      "bedrooms": 7.0,
      "neighborhood": null,
      "address_text": "East 24th Avenue, Vancouver, BC, V5R 1E8",
      "transit_minutes_to_ubc": 70
    },
    "rentals_ca:cmVudGFsbGlzdGluZzoxMTQ0NjE1": {
      "url": "https://rentals.ca/vancouver/west-36th-avenue",
      "title": "West 36th Avenue",
      "source": "rentals_ca",
      "price_cad": 1100,
      "bedrooms": 6.0,
      "neighborhood": null,
      "address_text": "West 36th Avenue, Vancouver, BC, V6N 2S7",
      "transit_minutes_to_ubc": 27
    },
    "rentals_ca:cmVudGFsbGlzdGluZzoxMzY1NDg5": {
      "url": "https://rentals.ca/vancouver/roomies-1365489",
      "title": null,
      "source": "rentals_ca",
      "price_cad": 1000,
      "bedrooms": 4.0,
      "neighborhood": null,
      "address_text": "Sunset, Vancouver, BC, V5W 3N3",
      "transit_minutes_to_ubc": 49
    },
    "rentals_ca:cmVudGFsbGlzdGluZzoxMDg4MjEw": {
      "url": "https://rentals.ca/vancouver/kensington-cedar-cottage-id1088210",
      "title": null,
      "source": "rentals_ca",
      "price_cad": 850,
      "bedrooms": 4.0,
      "neighborhood": null,
      "address_text": "Kensington - Cedar Cottage, Vancouver, BC, V5V 3B5",
      "transit_minutes_to_ubc": 55
    },
    "rentals_ca:cmVudGFsbGlzdGluZzoxMTk2MTkx": {
      "url": "https://rentals.ca/vancouver/roomies-1196191",
      "title": "Larch Street",
      "source": "rentals_ca",
      "price_cad": 1100,
      "bedrooms": 4.0,
      "neighborhood": null,
      "address_text": "Larch Street, Vancouver, BC, V6M 4E4",
      "transit_minutes_to_ubc": 32
    },
    "rentals_ca:cmVudGFsbGlzdGluZzoxMjAwMzMy": {
      "url": "https://rentals.ca/vancouver/3400-18th-avenue",
      "title": "3400 W 18TH AVENUE",
      "source": "rentals_ca",
      "price_cad": 6250,
      "bedrooms": 4.0,
      "neighborhood": null,
      "address_text": "3400 18TH Avenue, Vancouver, BC, V6S 1A7",
      "transit_minutes_to_ubc": 29
    },
    "rentals_ca:cmVudGFsbGlzdGluZzoxMTUyMzIz": {
      "url": "https://rentals.ca/vancouver/kerrisdale-id1152323",
      "title": null,
      "source": "rentals_ca",
      "price_cad": 1200,
      "bedrooms": 5.0,
      "neighborhood": null,
      "address_text": "Kerrisdale, Vancouver, BC, V6N 1B1",
      "transit_minutes_to_ubc": 30
    },
    "rentals_ca:cmVudGFsbGlzdGluZzoxMDY2Mzc0": {
      "url": "https://rentals.ca/vancouver/5290-trafalgar-street-4",
      "title": null,
      "source": "rentals_ca",
      "price_cad": 1080,
      "bedrooms": 4.0,
      "neighborhood": null,
      "address_text": "5290 Trafalgar Street, Vancouver, BC, V6N 2T5",
      "transit_minutes_to_ubc": 36
    },
    "rentals_ca:cmVudGFsbGlzdGluZzoxMTIwMzMw": {
      "url": "https://rentals.ca/vancouver/east-broadway-id1120330",
      "title": "East Broadway",
      "source": "rentals_ca",
      "price_cad": 820,
      "bedrooms": 5.0,
      "neighborhood": null,
      "address_text": "East Broadway, Vancouver, BC, V5N 1V6",
      "transit_minutes_to_ubc": 49
    },
    "rentals_ca:cmVudGFsbGlzdGluZzoxMjEyNTI0": {
      "url": "https://rentals.ca/vancouver/roomies-1212524",
      "title": "Beatty Street",
      "source": "rentals_ca",
      "price_cad": 850,
      "bedrooms": 4.0,
      "neighborhood": null,
      "address_text": "Beatty Street, Vancouver, BC, V6B 2M1",
      "transit_minutes_to_ubc": 53
    },
    "rentals_ca:cmVudGFsbGlzdGluZzoxMzcxNjYw": {
      "url": "https://rentals.ca/vancouver/3520-blenheim-street",
      "title": "3520 BLENHEIM STREET",
      "source": "rentals_ca",
      "price_cad": 6000,
      "bedrooms": 4.0,
      "neighborhood": null,
      "address_text": "3520 BLENHEIM STREET, Vancouver, BC, V6L 2X9",
      "transit_minutes_to_ubc": 25
    },
    "rentals_ca:cmVudGFsbGlzdGluZzo5NDg2NDg=": {
      "url": "https://rentals.ca/vancouver/homer-street-id948648",
      "title": "Homer Street",
      "source": "rentals_ca",
      "price_cad": 4200,
      "bedrooms": 4.0,
      "neighborhood": null,
      "address_text": "Homer Street, Vancouver, BC, V6B 6A7",
      "transit_minutes_to_ubc": 48
    },
    "rentals_ca:cmVudGFsbGlzdGluZzoxMTgxNzU1": {
      "url": "https://rentals.ca/vancouver/roomies-1181755",
      "title": null,
      "source": "rentals_ca",
      "price_cad": 790,
      "bedrooms": 5.0,
      "neighborhood": null,
      "address_text": "Victoria - Fraserview, Vancouver, BC, V5P 2V5",
      "transit_minutes_to_ubc": 48
    },
    "rentals_ca:cmVudGFsbGlzdGluZzo5MTM0NTE=": {
      "url": "https://rentals.ca/vancouver/keefer-place-id913451",
      "title": "Keefer Place",
      "source": "rentals_ca",
      "price_cad": 2000,
      "bedrooms": 4.0,
      "neighborhood": null,
      "address_text": "Keefer Place, Vancouver, BC, V6B 6N8",
      "transit_minutes_to_ubc": 54
    },
    "rentals_ca:cmVudGFsbGlzdGluZzoxMTkyMjE3": {
      "url": "https://rentals.ca/vancouver/roomies-1192217",
      "title": "East 28th Avenue",
      "source": "rentals_ca",
      "price_cad": 850,
      "bedrooms": 4.0,
      "neighborhood": null,
      "address_text": "East 28th Avenue, Vancouver, BC, V5R 1R4",
      "transit_minutes_to_ubc": 61
    },
    "rentals_ca:cmVudGFsbGlzdGluZzo5MTI0NzI=": {
      "url": "https://rentals.ca/vancouver/west-pender-street",
      "title": "West Pender Street",
      "source": "rentals_ca",
      "price_cad": 2200,
      "bedrooms": 4.0,
      "neighborhood": null,
      "address_text": "West Pender Street, Vancouver, BC, V6E 4S9",
      "transit_minutes_to_ubc": 47
    },
    "rentals_ca:cmVudGFsbGlzdGluZzoxMTU2NTQz": {
      "url": "https://rentals.ca/vancouver/4xxx-28-avenue",
      "title": "4xxx W 28 AVENUE",
      "source": "rentals_ca",
      "price_cad": 6500,
      "bedrooms": 5.0,
      "neighborhood": null,
      "address_text": "4xxx 28 Avenue, Vancouver, BC, V6S 1S7",
      "transit_minutes_to_ubc": 35
    },
    "rentals_ca:cmVudGFsbGlzdGluZzoxMzE1MzAz": {
      "url": "https://rentals.ca/vancouver/roomies-1315303",
      "title": null,
      "source": "rentals_ca",
      "price_cad": 1000,
      "bedrooms": 6.0,
      "neighborhood": null,
      "address_text": "Dunbar - Southlands, Vancouver, BC, V6N 1J4",
      "transit_minutes_to_ubc": 23
    }
  }
}